{"guide_annotations.md":"a848169c","guide_attributes.md":"7e48a5a5","guide_common-techniques.md":"b94da6f3","guide_cookbook.md":"f2422fe1","guide_faq.md":"416f203a","guide_generating-openapi-documents.md":"b497a31a","guide_index.md":"2c2c9594","guide_installation.md":"899df52f","guide_migrating-to-v3.md":"6bbaa75c","guide_migrating-to-v4.md":"7a4e1867","guide_required-elements.md":"76981bc0","guide_under-the-hood.md":"1908ac88","index.md":"0396399b","reference_annotations.md":"cffed514","reference_attributes.md":"9648e9ac","reference_generator.md":"08620489","reference_index.md":"ac15c5fe","reference_processors.md":"c8f3a9d7","related-projects.md":"272dae67","snippets_preamble_annotations.md":"6e1e8536","snippets_preamble_attributes.md":"a9783b73","snippets_preamble_processors.md":"14d882f2"}
